jimmysh_stock_api/__init__.py
jimmysh_stock_api/alphavantage.py
jimmysh_stock_api/google_finance.py
jimmysh_stock_api-0.0.3.dist-info/METADATA
jimmysh_stock_api-0.0.3.dist-info/RECORD
jimmysh_stock_api-0.0.3.dist-info/WHEEL
jimmysh_stock_api-0.0.3.dist-info/top_level.txt
