Metadata-Version: 2.1
Name: jimmysh-stock-api
Version: 0.0.3
Summary: A package for stock price
Home-page: https://github.com/pypa/sampleproject
Author: Kevin Liu
Author-email: qiankevinliu@gmail.com
License: UNKNOWN
Platform: UNKNOWN
Classifier: Programming Language :: Python :: 3
Classifier: License :: OSI Approved :: MIT License
Classifier: Operating System :: OS Independent
